{
  "lqi": {
    "width": 160,
    "height": 106
  },
  "xs3": {
    "width": 640,
    "height": 425
  },
  "xs2": {
    "width": 800,
    "height": 531
  },
  "xs": {
    "width": 960,
    "height": 637
  },
  "sm": {
    "width": 1120,
    "height": 744
  },
  "md": {
    "width": 1280,
    "height": 850
  },
  "lg": {
    "width": 1440,
    "height": 956
  },
  "xl": {
    "width": 1600,
    "height": 1062
  },
  "xl2": {
    "width": 1760,
    "height": 1168
  },
  "xl3": {
    "width": 1920,
    "height": 1275
  },
  "title": "The Annunciation",
  "artist": "Matthias Stom",
  "art_date": "c. 1633-1638",
  "art_medium": "Oil",
  "art_surface": "Canvas",
  "art_height": 113,
  "art_width": 166,
  "art_location": "Uffizi Gallery, Florence",
  "id": "08-08",
  "artwork_date": "2016-08-08T17:00:00.000Z",
  "cite_author": "Wikipedia",
  "cite_url": "https://commons.wikimedia.org/wiki/File:Matthias_Stomer_-_Annunciazione_-_Google_Art_Project.jpg",
  "orientation": "landscape",
  "vibrant": "#fcbc44",
  "lightVibrant": "#f4c66e",
  "darkVibrant": "#942a0f",
  "muted": "#5c8caa",
  "lightMuted": "#afbcb2",
  "darkMuted": "#293d52",
  "width": 3752,
  "height": 2491,
  "ratio": 0.663913,
  "hash": "9QmoShPCY3c",
  "maxWidth": "xl3"
}
